{"GlobalPropertiesHash":"IJxOxCCflyY0Dgd/NmYOTVjhnBX8z4tTgBtZlDfmeWE=","FingerprintPatternsHash":"gq3WsqcKBUGTSNle7RKKyXRIwh7M8ccEqOqYvIzoM04=","PropertyOverridesHash":"8ZRc1sGeVrPBx4lD717BgRaQekyh78QKV9SKsdt638U=","InputHashes":["2X1mMFTCWlho9izD7965rLIQZEMVGD8kSztu6fi/wjM=","F\u002ByJMZ5dQwq\u002Bua5Pff/GDFSTZk11CNX8U3P725ffQcc=","vBqIENX/E611bfSQb5Q0TwKAv\u002B/V5wQ9zuGgM/9HA08=","RJrWAXDDAY89VyxUCVsBqyyWQD9c50V2IhNZLGshUO0=","LB\u002BVvg5FOKo\u002BrI7NxKElar4CKTD3zciLZoaLJsEsLL8=","URXBqUGrT6bQAtkveQA7Gy6O9tsuz\u002B9vlVk4QQ1YhJ0=","a9g6mBw/\u002BoMcTXRDbib\u002BnHVTK8uFtHF9jozBV9PdwT0=","5d85K53YPW5zOXo0cjb4ZsiPzA1pwNNXbgeqgfAxUyw=","yRsE3y3\u002Bgnv34NQEd43XxYWB9N/M8LWQG2LUQCo2Paw=","Wk\u002B4DTq\u002BO\u002Bj2rJgXkKBP/r8taIWeJjvg\u002B4cJHjwZcfU=","g1N3wQ52VeyREmmUzEhxVghzN2KCwXx4rmHCrUo2T2Y=","OLzLhMbzjewuYb0\u002BbJPi2WfFXl8iIfKqI\u002BXE5CFzgRU=","PzmAVDqzyj/I5RhVvNPA46SUBUJ4Z3OAN9qBUTXtmNs=","ILt5gRLbI2XijRcVivKj4xd5awm1wO27w/TrzhCzbAM=","q4XV5I/RMghsxI7kW6NOMREni0jN0fIy2U5LMpfHOcA=","GMiPSWyonUUNL69zWgqYDumDoA33OAPOBKZAvf4me4Q=","WkRG1y4QOldjtvV/ewVp/7jntDFaaTnrjWpDk\u002BOsOcg=","10S9RDQRQaW1EwFr6ufapb8v59iqX8dTdH4w\u002B8Lwe0I=","swsYDCNyUedWIEmj6mMkA2Ciql2SNQBGL8I8ZDrLJs4=","OajHfOUq9S9TMsaL\u002BLRZT6DxlsA3bIte7WJSq9lb24Q="],"CachedAssets":{"2X1mMFTCWlho9izD7965rLIQZEMVGD8kSztu6fi/wjM=":{"Identity":"D:\\Flutter\\MusicAPI\\Music\\wwwroot\\audio\\76b17b9a-5eed-4d6b-8336-d86809096144.mp3","SourceId":"Music","SourceType":"Discovered","ContentRoot":"D:\\Flutter\\MusicAPI\\Music\\wwwroot\\","BasePath":"_content/Music","RelativePath":"audio/76b17b9a-5eed-4d6b-8336-d86809096144#[.{fingerprint}]?.mp3","AssetKind":"All","AssetMode":"All","AssetRole":"Primary","AssetMergeBehavior":null,"AssetMergeSource":"","RelatedAsset":null,"AssetTraitName":null,"AssetTraitValue":null,"Fingerprint":"5x8m738d03","Integrity":"qemgIKPQpd0HifPjokkCDZ7Ry9RBB6mRLgoqlUEmZzk=","CopyToOutputDirectory":"Never","CopyToPublishDirectory":"PreserveNewest","OriginalItemSpec":"wwwroot\\audio\\76b17b9a-5eed-4d6b-8336-d86809096144.mp3","FileLength":10604135,"LastWriteTime":"2025-12-22T16:25:46.7891503+00:00"},"F\u002ByJMZ5dQwq\u002Bua5Pff/GDFSTZk11CNX8U3P725ffQcc=":{"Identity":"D:\\Flutter\\MusicAPI\\Music\\wwwroot\\audio\\c6fadc81-203b-4e15-b91b-bba589652947.mp3","SourceId":"Music","SourceType":"Discovered","ContentRoot":"D:\\Flutter\\MusicAPI\\Music\\wwwroot\\","BasePath":"_content/Music","RelativePath":"audio/c6fadc81-203b-4e15-b91b-bba589652947#[.{fingerprint}]?.mp3","AssetKind":"All","AssetMode":"All","AssetRole":"Primary","AssetMergeBehavior":null,"AssetMergeSource":"","RelatedAsset":null,"AssetTraitName":null,"AssetTraitValue":null,"Fingerprint":"sgl3qfrie1","Integrity":"bLWFLJI\u002BIDkDoDLBCDO/a5afKGKX4pwl1zNqJYxPzdc=","CopyToOutputDirectory":"Never","CopyToPublishDirectory":"PreserveNewest","OriginalItemSpec":"wwwroot\\audio\\c6fadc81-203b-4e15-b91b-bba589652947.mp3","FileLength":4954353,"LastWriteTime":"2025-12-22T16:25:46.8320718+00:00"},"vBqIENX/E611bfSQb5Q0TwKAv\u002B/V5wQ9zuGgM/9HA08=":{"Identity":"D:\\Flutter\\MusicAPI\\Music\\wwwroot\\audio\\e9271ff1-98ca-4a1c-a5e0-cad1687d26b4.mp3","SourceId":"Music","SourceType":"Discovered","ContentRoot":"D:\\Flutter\\MusicAPI\\Music\\wwwroot\\","BasePath":"_content/Music","RelativePath":"audio/e9271ff1-98ca-4a1c-a5e0-cad1687d26b4#[.{fingerprint}]?.mp3","AssetKind":"All","AssetMode":"All","AssetRole":"Primary","AssetMergeBehavior":null,"AssetMergeSource":"","RelatedAsset":null,"AssetTraitName":null,"AssetTraitValue":null,"Fingerprint":"6gxb84sehz","Integrity":"FlZa8X5xvRUb8AuDsnl0fag1NPgKKg8EviqGjBWbH2c=","CopyToOutputDirectory":"Never","CopyToPublishDirectory":"PreserveNewest","OriginalItemSpec":"wwwroot\\audio\\e9271ff1-98ca-4a1c-a5e0-cad1687d26b4.mp3","FileLength":9232199,"LastWriteTime":"2025-12-22T16:25:46.9118202+00:00"},"RJrWAXDDAY89VyxUCVsBqyyWQD9c50V2IhNZLGshUO0=":{"Identity":"D:\\Flutter\\MusicAPI\\Music\\wwwroot\\audio\\ef573c7b-9a9b-462a-a927-5f49feac7c9b.mp3","SourceId":"Music","SourceType":"Discovered","ContentRoot":"D:\\Flutter\\MusicAPI\\Music\\wwwroot\\","BasePath":"_content/Music","RelativePath":"audio/ef573c7b-9a9b-462a-a927-5f49feac7c9b#[.{fingerprint}]?.mp3","AssetKind":"All","AssetMode":"All","AssetRole":"Primary","AssetMergeBehavior":null,"AssetMergeSource":"","RelatedAsset":null,"AssetTraitName":null,"AssetTraitValue":null,"Fingerprint":"6asbhabbhx","Integrity":"EhOCziLbZBfF\u002BCTakl2z0GAsniVSnOvrMLOMmRv0VEc=","CopyToOutputDirectory":"Never","CopyToPublishDirectory":"PreserveNewest","OriginalItemSpec":"wwwroot\\audio\\ef573c7b-9a9b-462a-a927-5f49feac7c9b.mp3","FileLength":6439208,"LastWriteTime":"2025-12-22T16:25:46.9656764+00:00"},"LB\u002BVvg5FOKo\u002BrI7NxKElar4CKTD3zciLZoaLJsEsLL8=":{"Identity":"D:\\Flutter\\MusicAPI\\Music\\wwwroot\\audio\\f7e55a63-7753-4652-8dd5-2c8da2008b93.mp3","SourceId":"Music","SourceType":"Discovered","ContentRoot":"D:\\Flutter\\MusicAPI\\Music\\wwwroot\\","BasePath":"_content/Music","RelativePath":"audio/f7e55a63-7753-4652-8dd5-2c8da2008b93#[.{fingerprint}]?.mp3","AssetKind":"All","AssetMode":"All","AssetRole":"Primary","AssetMergeBehavior":null,"AssetMergeSource":"","RelatedAsset":null,"AssetTraitName":null,"AssetTraitValue":null,"Fingerprint":"d9tq8cfkkc","Integrity":"ob4i536fOTBXs8vWx2NljBpPK2oQ37x\u002BOBaENYhTW3w=","CopyToOutputDirectory":"Never","CopyToPublishDirectory":"PreserveNewest","OriginalItemSpec":"wwwroot\\audio\\f7e55a63-7753-4652-8dd5-2c8da2008b93.mp3","FileLength":7710866,"LastWriteTime":"2025-12-22T16:25:47.0335218+00:00"},"URXBqUGrT6bQAtkveQA7Gy6O9tsuz\u002B9vlVk4QQ1YhJ0=":{"Identity":"D:\\Flutter\\MusicAPI\\Music\\wwwroot\\audio\\f9545321-1765-4340-a11c-afbe28480f51.mp3","SourceId":"Music","SourceType":"Discovered","ContentRoot":"D:\\Flutter\\MusicAPI\\Music\\wwwroot\\","BasePath":"_content/Music","RelativePath":"audio/f9545321-1765-4340-a11c-afbe28480f51#[.{fingerprint}]?.mp3","AssetKind":"All","AssetMode":"All","AssetRole":"Primary","AssetMergeBehavior":null,"AssetMergeSource":"","RelatedAsset":null,"AssetTraitName":null,"AssetTraitValue":null,"Fingerprint":"cxppez0m5n","Integrity":"gPaXS9Js5U7qnHpbc\u002BLRqjyQSVeeKdkFH0g0D/ALAbM=","CopyToOutputDirectory":"Never","CopyToPublishDirectory":"PreserveNewest","OriginalItemSpec":"wwwroot\\audio\\f9545321-1765-4340-a11c-afbe28480f51.mp3","FileLength":9592665,"LastWriteTime":"2025-12-22T16:25:47.1202649+00:00"},"a9g6mBw/\u002BoMcTXRDbib\u002BnHVTK8uFtHF9jozBV9PdwT0=":{"Identity":"D:\\Flutter\\MusicAPI\\Music\\wwwroot\\avatar_artist\\artist_0a783db2-8f2f-499a-b7a7-ced2ca004ac3.png","SourceId":"Music","SourceType":"Discovered","ContentRoot":"D:\\Flutter\\MusicAPI\\Music\\wwwroot\\","BasePath":"_content/Music","RelativePath":"avatar_artist/artist_0a783db2-8f2f-499a-b7a7-ced2ca004ac3#[.{fingerprint}]?.png","AssetKind":"All","AssetMode":"All","AssetRole":"Primary","AssetMergeBehavior":null,"AssetMergeSource":"","RelatedAsset":null,"AssetTraitName":null,"AssetTraitValue":null,"Fingerprint":"6fjh2jprom","Integrity":"kjoTWsIxjH9cOKLPQsFYV5PYQSJiQhDcqpmmrTbj684=","CopyToOutputDirectory":"Never","CopyToPublishDirectory":"PreserveNewest","OriginalItemSpec":"wwwroot\\avatar_artist\\artist_0a783db2-8f2f-499a-b7a7-ced2ca004ac3.png","FileLength":72509,"LastWriteTime":"2025-12-22T16:25:47.1222603+00:00"},"5d85K53YPW5zOXo0cjb4ZsiPzA1pwNNXbgeqgfAxUyw=":{"Identity":"D:\\Flutter\\MusicAPI\\Music\\wwwroot\\avatar_artist\\artist_e88aa615-6c3b-4ec3-bc70-032150cc677e.png","SourceId":"Music","SourceType":"Discovered","ContentRoot":"D:\\Flutter\\MusicAPI\\Music\\wwwroot\\","BasePath":"_content/Music","RelativePath":"avatar_artist/artist_e88aa615-6c3b-4ec3-bc70-032150cc677e#[.{fingerprint}]?.png","AssetKind":"All","AssetMode":"All","AssetRole":"Primary","AssetMergeBehavior":null,"AssetMergeSource":"","RelatedAsset":null,"AssetTraitName":null,"AssetTraitValue":null,"Fingerprint":"xbsbef5el9","Integrity":"02GVMN7YY0Dj9qh5oD69pwnqNeR707Tl5wvywbb2\u002BcU=","CopyToOutputDirectory":"Never","CopyToPublishDirectory":"PreserveNewest","OriginalItemSpec":"wwwroot\\avatar_artist\\artist_e88aa615-6c3b-4ec3-bc70-032150cc677e.png","FileLength":180838,"LastWriteTime":"2025-12-22T16:25:47.1232574+00:00"},"yRsE3y3\u002Bgnv34NQEd43XxYWB9N/M8LWQG2LUQCo2Paw=":{"Identity":"D:\\Flutter\\MusicAPI\\Music\\wwwroot\\avatar_artist\\artist_f7ae1c19-d4ce-469c-8a4a-5fe4fe3406f6.png","SourceId":"Music","SourceType":"Discovered","ContentRoot":"D:\\Flutter\\MusicAPI\\Music\\wwwroot\\","BasePath":"_content/Music","RelativePath":"avatar_artist/artist_f7ae1c19-d4ce-469c-8a4a-5fe4fe3406f6#[.{fingerprint}]?.png","AssetKind":"All","AssetMode":"All","AssetRole":"Primary","AssetMergeBehavior":null,"AssetMergeSource":"","RelatedAsset":null,"AssetTraitName":null,"AssetTraitValue":null,"Fingerprint":"nszwx4cf4j","Integrity":"N06qrytcQulBx2UgBNH\u002Bs28om2e3Dr8hj1Jer\u002B0bYsM=","CopyToOutputDirectory":"Never","CopyToPublishDirectory":"PreserveNewest","OriginalItemSpec":"wwwroot\\avatar_artist\\artist_f7ae1c19-d4ce-469c-8a4a-5fe4fe3406f6.png","FileLength":110420,"LastWriteTime":"2025-12-22T16:25:47.1242541+00:00"},"Wk\u002B4DTq\u002BO\u002Bj2rJgXkKBP/r8taIWeJjvg\u002B4cJHjwZcfU=":{"Identity":"D:\\Flutter\\MusicAPI\\Music\\wwwroot\\covers\\1ea3c303-35db-42b3-91d3-ac032c1c1ebe.png","SourceId":"Music","SourceType":"Discovered","ContentRoot":"D:\\Flutter\\MusicAPI\\Music\\wwwroot\\","BasePath":"_content/Music","RelativePath":"covers/1ea3c303-35db-42b3-91d3-ac032c1c1ebe#[.{fingerprint}]?.png","AssetKind":"All","AssetMode":"All","AssetRole":"Primary","AssetMergeBehavior":null,"AssetMergeSource":"","RelatedAsset":null,"AssetTraitName":null,"AssetTraitValue":null,"Fingerprint":"e1spkfbin3","Integrity":"MrpLvBrMI6ApE7g2JmKi5rpgDbP7wdhIj6kCBZeBXaU=","CopyToOutputDirectory":"Never","CopyToPublishDirectory":"PreserveNewest","OriginalItemSpec":"wwwroot\\covers\\1ea3c303-35db-42b3-91d3-ac032c1c1ebe.png","FileLength":120940,"LastWriteTime":"2025-12-22T16:25:47.1252516+00:00"},"g1N3wQ52VeyREmmUzEhxVghzN2KCwXx4rmHCrUo2T2Y=":{"Identity":"D:\\Flutter\\MusicAPI\\Music\\wwwroot\\covers\\3f3dc9c9-c222-4ef6-a212-5fba7f1379af.png","SourceId":"Music","SourceType":"Discovered","ContentRoot":"D:\\Flutter\\MusicAPI\\Music\\wwwroot\\","BasePath":"_content/Music","RelativePath":"covers/3f3dc9c9-c222-4ef6-a212-5fba7f1379af#[.{fingerprint}]?.png","AssetKind":"All","AssetMode":"All","AssetRole":"Primary","AssetMergeBehavior":null,"AssetMergeSource":"","RelatedAsset":null,"AssetTraitName":null,"AssetTraitValue":null,"Fingerprint":"478lhcf7h8","Integrity":"wC251GQ3XnNEJwOfXDGNp\u002BIWFpCTv0BBvmazKjhatwA=","CopyToOutputDirectory":"Never","CopyToPublishDirectory":"PreserveNewest","OriginalItemSpec":"wwwroot\\covers\\3f3dc9c9-c222-4ef6-a212-5fba7f1379af.png","FileLength":159518,"LastWriteTime":"2025-12-22T16:25:47.1272456+00:00"},"OLzLhMbzjewuYb0\u002BbJPi2WfFXl8iIfKqI\u002BXE5CFzgRU=":{"Identity":"D:\\Flutter\\MusicAPI\\Music\\wwwroot\\covers\\571edf0f-29ff-4997-ba71-f59414ceb308.png","SourceId":"Music","SourceType":"Discovered","ContentRoot":"D:\\Flutter\\MusicAPI\\Music\\wwwroot\\","BasePath":"_content/Music","RelativePath":"covers/571edf0f-29ff-4997-ba71-f59414ceb308#[.{fingerprint}]?.png","AssetKind":"All","AssetMode":"All","AssetRole":"Primary","AssetMergeBehavior":null,"AssetMergeSource":"","RelatedAsset":null,"AssetTraitName":null,"AssetTraitValue":null,"Fingerprint":"9pjlz8o6d5","Integrity":"A4Z62T9fs3KsnZfaTWGuYORRoKRuozWR5vY8eDdfPAw=","CopyToOutputDirectory":"Never","CopyToPublishDirectory":"PreserveNewest","OriginalItemSpec":"wwwroot\\covers\\571edf0f-29ff-4997-ba71-f59414ceb308.png","FileLength":122131,"LastWriteTime":"2025-12-22T16:25:47.1282419+00:00"},"PzmAVDqzyj/I5RhVvNPA46SUBUJ4Z3OAN9qBUTXtmNs=":{"Identity":"D:\\Flutter\\MusicAPI\\Music\\wwwroot\\covers\\89238e32-6d04-4c95-ba34-8c5379f702f8.png","SourceId":"Music","SourceType":"Discovered","ContentRoot":"D:\\Flutter\\MusicAPI\\Music\\wwwroot\\","BasePath":"_content/Music","RelativePath":"covers/89238e32-6d04-4c95-ba34-8c5379f702f8#[.{fingerprint}]?.png","AssetKind":"All","AssetMode":"All","AssetRole":"Primary","AssetMergeBehavior":null,"AssetMergeSource":"","RelatedAsset":null,"AssetTraitName":null,"AssetTraitValue":null,"Fingerprint":"1eaz1ins0b","Integrity":"Wbi3tjBhzO1wGfu3cYX\u002BM4PCiximUimWlTotFmJv\u002BN0=","CopyToOutputDirectory":"Never","CopyToPublishDirectory":"PreserveNewest","OriginalItemSpec":"wwwroot\\covers\\89238e32-6d04-4c95-ba34-8c5379f702f8.png","FileLength":226706,"LastWriteTime":"2025-12-22T16:25:47.1292745+00:00"},"ILt5gRLbI2XijRcVivKj4xd5awm1wO27w/TrzhCzbAM=":{"Identity":"D:\\Flutter\\MusicAPI\\Music\\wwwroot\\covers\\d9d5abfc-b91e-4e55-abf2-8224c977b7f8.png","SourceId":"Music","SourceType":"Discovered","ContentRoot":"D:\\Flutter\\MusicAPI\\Music\\wwwroot\\","BasePath":"_content/Music","RelativePath":"covers/d9d5abfc-b91e-4e55-abf2-8224c977b7f8#[.{fingerprint}]?.png","AssetKind":"All","AssetMode":"All","AssetRole":"Primary","AssetMergeBehavior":null,"AssetMergeSource":"","RelatedAsset":null,"AssetTraitName":null,"AssetTraitValue":null,"Fingerprint":"cj7xdi41dd","Integrity":"mCbwhedsbVL2GOX75Rwr3JhrRECOAfU5dhfyauWQ8Qg=","CopyToOutputDirectory":"Never","CopyToPublishDirectory":"PreserveNewest","OriginalItemSpec":"wwwroot\\covers\\d9d5abfc-b91e-4e55-abf2-8224c977b7f8.png","FileLength":127202,"LastWriteTime":"2025-12-22T16:25:47.1302376+00:00"},"q4XV5I/RMghsxI7kW6NOMREni0jN0fIy2U5LMpfHOcA=":{"Identity":"D:\\Flutter\\MusicAPI\\Music\\wwwroot\\covers\\fbac023a-b8cd-4b23-92c9-f19dfc39a190.png","SourceId":"Music","SourceType":"Discovered","ContentRoot":"D:\\Flutter\\MusicAPI\\Music\\wwwroot\\","BasePath":"_content/Music","RelativePath":"covers/fbac023a-b8cd-4b23-92c9-f19dfc39a190#[.{fingerprint}]?.png","AssetKind":"All","AssetMode":"All","AssetRole":"Primary","AssetMergeBehavior":null,"AssetMergeSource":"","RelatedAsset":null,"AssetTraitName":null,"AssetTraitValue":null,"Fingerprint":"cj7xdi41dd","Integrity":"mCbwhedsbVL2GOX75Rwr3JhrRECOAfU5dhfyauWQ8Qg=","CopyToOutputDirectory":"Never","CopyToPublishDirectory":"PreserveNewest","OriginalItemSpec":"wwwroot\\covers\\fbac023a-b8cd-4b23-92c9-f19dfc39a190.png","FileLength":127202,"LastWriteTime":"2025-12-22T16:25:47.1312355+00:00"},"10S9RDQRQaW1EwFr6ufapb8v59iqX8dTdH4w\u002B8Lwe0I=":{"Identity":"D:\\Flutter\\MusicAPI\\Music\\wwwroot\\uploads\\avatars\\avatar_1_f9946302-2b25-4772-8627-2e45ba301f9d.jpg","SourceId":"Music","SourceType":"Discovered","ContentRoot":"D:\\Flutter\\MusicAPI\\Music\\wwwroot\\","BasePath":"_content/Music","RelativePath":"uploads/avatars/avatar_1_f9946302-2b25-4772-8627-2e45ba301f9d#[.{fingerprint}]?.jpg","AssetKind":"All","AssetMode":"All","AssetRole":"Primary","AssetMergeBehavior":null,"AssetMergeSource":"","RelatedAsset":null,"AssetTraitName":null,"AssetTraitValue":null,"Fingerprint":"94gpst5xfl","Integrity":"2d14Zse56qkCUMoYlNiXumRPlqxhhH4UmUdoLoc5b/E=","CopyToOutputDirectory":"Never","CopyToPublishDirectory":"PreserveNewest","OriginalItemSpec":"wwwroot\\uploads\\avatars\\avatar_1_f9946302-2b25-4772-8627-2e45ba301f9d.jpg","FileLength":69346,"LastWriteTime":"2025-12-22T16:25:47.1322322+00:00"},"GMiPSWyonUUNL69zWgqYDumDoA33OAPOBKZAvf4me4Q=":{"Identity":"D:\\Flutter\\MusicAPI\\Music\\wwwroot\\uploads\\avatars\\avatar_1_69ef6753-8463-4e06-9426-b5fd50313b81.jpg","SourceId":"Music","SourceType":"Discovered","ContentRoot":"D:\\Flutter\\MusicAPI\\Music\\wwwroot\\","BasePath":"_content/Music","RelativePath":"uploads/avatars/avatar_1_69ef6753-8463-4e06-9426-b5fd50313b81#[.{fingerprint}]?.jpg","AssetKind":"All","AssetMode":"All","AssetRole":"Primary","AssetMergeBehavior":null,"AssetMergeSource":"","RelatedAsset":null,"AssetTraitName":null,"AssetTraitValue":null,"Fingerprint":"yqbtd14zmx","Integrity":"Rk7K7PoR2EuD\u002BnMFk/VwfbPii2k\u002BT8/5jMN\u002BzGvogss=","CopyToOutputDirectory":"Never","CopyToPublishDirectory":"PreserveNewest","OriginalItemSpec":"wwwroot\\uploads\\avatars\\avatar_1_69ef6753-8463-4e06-9426-b5fd50313b81.jpg","FileLength":31195,"LastWriteTime":"2025-12-22T20:17:40.008397+00:00"},"WkRG1y4QOldjtvV/ewVp/7jntDFaaTnrjWpDk\u002BOsOcg=":{"Identity":"D:\\Flutter\\MusicAPI\\Music\\wwwroot\\uploads\\avatars\\avatar_1_e1eefd5e-d675-4809-996e-debfd317e9de.jpg","SourceId":"Music","SourceType":"Discovered","ContentRoot":"D:\\Flutter\\MusicAPI\\Music\\wwwroot\\","BasePath":"_content/Music","RelativePath":"uploads/avatars/avatar_1_e1eefd5e-d675-4809-996e-debfd317e9de#[.{fingerprint}]?.jpg","AssetKind":"All","AssetMode":"All","AssetRole":"Primary","AssetMergeBehavior":null,"AssetMergeSource":"","RelatedAsset":null,"AssetTraitName":null,"AssetTraitValue":null,"Fingerprint":"yqbtd14zmx","Integrity":"Rk7K7PoR2EuD\u002BnMFk/VwfbPii2k\u002BT8/5jMN\u002BzGvogss=","CopyToOutputDirectory":"Never","CopyToPublishDirectory":"PreserveNewest","OriginalItemSpec":"wwwroot\\uploads\\avatars\\avatar_1_e1eefd5e-d675-4809-996e-debfd317e9de.jpg","FileLength":31195,"LastWriteTime":"2025-12-22T20:17:40.0093945+00:00"}},"CachedCopyCandidates":{}}